{
    "steps": [
        {
            "step": 0,
            "dsl_ys": [
                ""
            ],
            "new_dsl_ys": [
                "obj_color(state, object3, 8)",
                "obj_color(state, object1, 8)",
                "`obj_color(state, object3, 8)`"
            ],
            "values": [
                21.001,
                21.001,
                1.0
            ],
            "select_new_ys": [
                "obj_color(state, object3, 8)",
                "obj_color(state, object1, 8)"
            ]
        },
        {
            "step": 1,
            "dsl_ys": [
                "obj_color(state, object3, 8)",
                "obj_color(state, object1, 8)"
            ],
            "new_dsl_ys": [
                "obj_color(state, object3, 8)->obj_color(state, object4, 8)",
                "obj_color(state, object3, 8)->obj_color(state, object4, 8)",
                "obj_color(state, object3, 8)->obj_color(state, object4, 8)",
                "obj_color(state, object1, 8)->obj_color(state, object2, 8)",
                "obj_color(state, object1, 8)->obj_color(state, object2, 8)",
                "obj_color(state, object1, 8)->obj_color(state, object2, 8)"
            ],
            "values": [
                1.0,
                1.0,
                1.0,
                0.001,
                0.001,
                0.001
            ],
            "select_new_ys": [
                "obj_color(state, object3, 8)->obj_color(state, object4, 8)",
                "obj_color(state, object3, 8)->obj_color(state, object4, 8)"
            ]
        },
        {
            "step": 2,
            "dsl_ys": [
                "obj_color(state, object3, 8)->obj_color(state, object4, 8)",
                "obj_color(state, object3, 8)->obj_color(state, object4, 8)"
            ],
            "new_dsl_ys": [
                "obj_color(state, object3, 8)->obj_color(state, object4, 8)->obj_color(state, object10, 8)",
                "obj_color(state, object3, 8)->obj_color(state, object4, 8)->obj_color(state, object10, 8)",
                "obj_color(state, object3, 8)->obj_color(state, object4, 8)->obj_color(state, object10, 8)",
                "obj_color(state, object3, 8)->obj_color(state, object4, 8)->obj_color(state, object5, 8)",
                "obj_color(state, object3, 8)->obj_color(state, object4, 8)->obj_color(state, object5, 8)",
                "obj_color(state, object3, 8)->obj_color(state, object4, 8)->obj_color(state, object5, 8)"
            ],
            "values": [
                20.0,
                20.0,
                20.0,
                21.0,
                21.0,
                21.0
            ],
            "select_new_ys": [
                "obj_color(state, object3, 8)->obj_color(state, object4, 8)->obj_color(state, object5, 8)",
                "obj_color(state, object3, 8)->obj_color(state, object4, 8)->obj_color(state, object5, 8)"
            ]
        },
        {
            "step": 3,
            "dsl_ys": [
                "obj_color(state, object3, 8)->obj_color(state, object4, 8)->obj_color(state, object5, 8)",
                "obj_color(state, object3, 8)->obj_color(state, object4, 8)->obj_color(state, object5, 8)"
            ],
            "new_dsl_ys": [
                "obj_color(state, object3, 8)->obj_color(state, object4, 8)->obj_color(state, object5, 8)->obj_color(state, object6, 8)",
                "obj_color(state, object3, 8)->obj_color(state, object4, 8)->obj_color(state, object5, 8)->obj_color(state, object6, 8)",
                "obj_color(state, object3, 8)->obj_color(state, object4, 8)->obj_color(state, object5, 8)->obj_color(state, object6, 8)",
                "obj_color(state, object3, 8)->obj_color(state, object4, 8)->obj_color(state, object5, 8)->obj_color(state, object6, 8)",
                "obj_color(state, object3, 8)->obj_color(state, object4, 8)->obj_color(state, object5, 8)->obj_color(state, object6, 8)",
                "obj_color(state, object3, 8)->obj_color(state, object4, 8)->obj_color(state, object5, 8)->obj_color(state, object6, 8)"
            ],
            "values": [
                21.001,
                21.001,
                21.001,
                21.001,
                21.001,
                21.001
            ],
            "select_new_ys": [
                "obj_color(state, object3, 8)->obj_color(state, object4, 8)->obj_color(state, object5, 8)->obj_color(state, object6, 8)",
                "obj_color(state, object3, 8)->obj_color(state, object4, 8)->obj_color(state, object5, 8)->obj_color(state, object6, 8)"
            ]
        },
        {
            "step": 4,
            "dsl_ys": [
                "obj_color(state, object3, 8)->obj_color(state, object4, 8)->obj_color(state, object5, 8)->obj_color(state, object6, 8)",
                "obj_color(state, object3, 8)->obj_color(state, object4, 8)->obj_color(state, object5, 8)->obj_color(state, object6, 8)"
            ],
            "new_dsl_ys": [
                "obj_color(state, object3, 8)->obj_color(state, object4, 8)->obj_color(state, object5, 8)->obj_color(state, object6, 8)->obj_color(state, object7, 8)",
                "obj_color(state, object3, 8)->obj_color(state, object4, 8)->obj_color(state, object5, 8)->obj_color(state, object6, 8)->obj_color(state, object10, 8)",
                "obj_color(state, object3, 8)->obj_color(state, object4, 8)->obj_color(state, object5, 8)->obj_color(state, object6, 8)->obj_color(state, object7, 8)",
                "obj_color(state, object3, 8)->obj_color(state, object4, 8)->obj_color(state, object5, 8)->obj_color(state, object6, 8)->obj_color(state, object7, 8)",
                "obj_color(state, object3, 8)->obj_color(state, object4, 8)->obj_color(state, object5, 8)->obj_color(state, object6, 8)->obj_color(state, object7, 8)",
                "obj_color(state, object3, 8)->obj_color(state, object4, 8)->obj_color(state, object5, 8)->obj_color(state, object6, 8)->obj_color(state, object7, 8)"
            ],
            "values": [
                20.0,
                0.0,
                20.0,
                20.0,
                20.0,
                20.0
            ],
            "select_new_ys": [
                "obj_color(state, object3, 8)->obj_color(state, object4, 8)->obj_color(state, object5, 8)->obj_color(state, object6, 8)->obj_color(state, object7, 8)",
                "obj_color(state, object3, 8)->obj_color(state, object4, 8)->obj_color(state, object5, 8)->obj_color(state, object6, 8)->obj_color(state, object7, 8)"
            ]
        },
        {
            "step": 5,
            "dsl_ys": [
                "obj_color(state, object3, 8)->obj_color(state, object4, 8)->obj_color(state, object5, 8)->obj_color(state, object6, 8)->obj_color(state, object7, 8)",
                "obj_color(state, object3, 8)->obj_color(state, object4, 8)->obj_color(state, object5, 8)->obj_color(state, object6, 8)->obj_color(state, object7, 8)"
            ],
            "new_dsl_ys": [
                "obj_color(state, object3, 8)->obj_color(state, object4, 8)->obj_color(state, object5, 8)->obj_color(state, object6, 8)->obj_color(state, object7, 8)->obj_color(state, object8, 8)",
                "obj_color(state, object3, 8)->obj_color(state, object4, 8)->obj_color(state, object5, 8)->obj_color(state, object6, 8)->obj_color(state, object7, 8)->obj_color(state, object8, 8)",
                "obj_color(state, object3, 8)->obj_color(state, object4, 8)->obj_color(state, object5, 8)->obj_color(state, object6, 8)->obj_color(state, object7, 8)->obj_color(state, object10, 8)",
                "obj_color(state, object3, 8)->obj_color(state, object4, 8)->obj_color(state, object5, 8)->obj_color(state, object6, 8)->obj_color(state, object7, 8)->obj_color(state, object8, 8)",
                "obj_color(state, object3, 8)->obj_color(state, object4, 8)->obj_color(state, object5, 8)->obj_color(state, object6, 8)->obj_color(state, object7, 8)->obj_color(state, object8, 8)",
                "obj_color(state, object3, 8)->obj_color(state, object4, 8)->obj_color(state, object5, 8)->obj_color(state, object6, 8)->obj_color(state, object7, 8)->obj_color(state, object8, 8)"
            ],
            "values": [
                1.0,
                1.0,
                1.0,
                1.0,
                1.0,
                1.0
            ],
            "select_new_ys": [
                "obj_color(state, object3, 8)->obj_color(state, object4, 8)->obj_color(state, object5, 8)->obj_color(state, object6, 8)->obj_color(state, object7, 8)->obj_color(state, object8, 8)",
                "obj_color(state, object3, 8)->obj_color(state, object4, 8)->obj_color(state, object5, 8)->obj_color(state, object6, 8)->obj_color(state, object7, 8)->obj_color(state, object8, 8)"
            ]
        },
        {
            "step": 6,
            "dsl_ys": [
                "obj_color(state, object3, 8)->obj_color(state, object4, 8)->obj_color(state, object5, 8)->obj_color(state, object6, 8)->obj_color(state, object7, 8)->obj_color(state, object8, 8)",
                "obj_color(state, object3, 8)->obj_color(state, object4, 8)->obj_color(state, object5, 8)->obj_color(state, object6, 8)->obj_color(state, object7, 8)->obj_color(state, object8, 8)"
            ],
            "new_dsl_ys": [
                "obj_color(state, object3, 8)->obj_color(state, object4, 8)->obj_color(state, object5, 8)->obj_color(state, object6, 8)->obj_color(state, object7, 8)->obj_color(state, object8, 8)->obj_color(state, object9, 8)",
                "obj_color(state, object3, 8)->obj_color(state, object4, 8)->obj_color(state, object5, 8)->obj_color(state, object6, 8)->obj_color(state, object7, 8)->obj_color(state, object8, 8)->obj_color(state, object9, 8)",
                "obj_color(state, object3, 8)->obj_color(state, object4, 8)->obj_color(state, object5, 8)->obj_color(state, object6, 8)->obj_color(state, object7, 8)->obj_color(state, object8, 8)->obj_color(state, object9, 8)",
                "obj_color(state, object3, 8)->obj_color(state, object4, 8)->obj_color(state, object5, 8)->obj_color(state, object6, 8)->obj_color(state, object7, 8)->obj_color(state, object8, 8)->obj_color(state, object9, 8)",
                "obj_color(state, object3, 8)->obj_color(state, object4, 8)->obj_color(state, object5, 8)->obj_color(state, object6, 8)->obj_color(state, object7, 8)->obj_color(state, object8, 8)->obj_color(state, object9, 8)",
                "obj_color(state, object3, 8)->obj_color(state, object4, 8)->obj_color(state, object5, 8)->obj_color(state, object6, 8)->obj_color(state, object7, 8)->obj_color(state, object8, 8)->obj_color(state, object9, 8)"
            ],
            "values": [
                0.0,
                0.0,
                0.0,
                0.0,
                0.0,
                0.0
            ],
            "select_new_ys": [
                "obj_color(state, object3, 8)->obj_color(state, object4, 8)->obj_color(state, object5, 8)->obj_color(state, object6, 8)->obj_color(state, object7, 8)->obj_color(state, object8, 8)->obj_color(state, object9, 8)",
                "obj_color(state, object3, 8)->obj_color(state, object4, 8)->obj_color(state, object5, 8)->obj_color(state, object6, 8)->obj_color(state, object7, 8)->obj_color(state, object8, 8)->obj_color(state, object9, 8)"
            ]
        },
        {
            "step": 7,
            "dsl_ys": [
                "obj_color(state, object3, 8)->obj_color(state, object4, 8)->obj_color(state, object5, 8)->obj_color(state, object6, 8)->obj_color(state, object7, 8)->obj_color(state, object8, 8)->obj_color(state, object9, 8)",
                "obj_color(state, object3, 8)->obj_color(state, object4, 8)->obj_color(state, object5, 8)->obj_color(state, object6, 8)->obj_color(state, object7, 8)->obj_color(state, object8, 8)->obj_color(state, object9, 8)"
            ],
            "new_dsl_ys": [
                "obj_color(state, object3, 8)->obj_color(state, object4, 8)->obj_color(state, object5, 8)->obj_color(state, object6, 8)->obj_color(state, object7, 8)->obj_color(state, object8, 8)->obj_color(state, object9, 8)->obj_color(state, object10, 8)",
                "obj_color(state, object3, 8)->obj_color(state, object4, 8)->obj_color(state, object5, 8)->obj_color(state, object6, 8)->obj_color(state, object7, 8)->obj_color(state, object8, 8)->obj_color(state, object9, 8)->obj_color(state, object10, 8)",
                "obj_color(state, object3, 8)->obj_color(state, object4, 8)->obj_color(state, object5, 8)->obj_color(state, object6, 8)->obj_color(state, object7, 8)->obj_color(state, object8, 8)->obj_color(state, object9, 8)->obj_color(state, object10, 8)",
                "obj_color(state, object3, 8)->obj_color(state, object4, 8)->obj_color(state, object5, 8)->obj_color(state, object6, 8)->obj_color(state, object7, 8)->obj_color(state, object8, 8)->obj_color(state, object9, 8)->obj_color(state, object10, 8)",
                "obj_color(state, object3, 8)->obj_color(state, object4, 8)->obj_color(state, object5, 8)->obj_color(state, object6, 8)->obj_color(state, object7, 8)->obj_color(state, object8, 8)->obj_color(state, object9, 8)->obj_color(state, object10, 8)"
            ],
            "values": [
                0.0,
                0.0,
                0.0,
                0.0,
                0.0
            ],
            "select_new_ys": [
                "obj_color(state, object3, 8)->obj_color(state, object4, 8)->obj_color(state, object5, 8)->obj_color(state, object6, 8)->obj_color(state, object7, 8)->obj_color(state, object8, 8)->obj_color(state, object9, 8)->obj_color(state, object10, 8)",
                "obj_color(state, object3, 8)->obj_color(state, object4, 8)->obj_color(state, object5, 8)->obj_color(state, object6, 8)->obj_color(state, object7, 8)->obj_color(state, object8, 8)->obj_color(state, object9, 8)->obj_color(state, object10, 8)"
            ]
        },
        {
            "step": 8,
            "dsl_ys": [
                "obj_color(state, object3, 8)->obj_color(state, object4, 8)->obj_color(state, object5, 8)->obj_color(state, object6, 8)->obj_color(state, object7, 8)->obj_color(state, object8, 8)->obj_color(state, object9, 8)->obj_color(state, object10, 8)",
                "obj_color(state, object3, 8)->obj_color(state, object4, 8)->obj_color(state, object5, 8)->obj_color(state, object6, 8)->obj_color(state, object7, 8)->obj_color(state, object8, 8)->obj_color(state, object9, 8)->obj_color(state, object10, 8)"
            ],
            "new_dsl_ys": [
                "obj_color(state, object3, 8)->obj_color(state, object4, 8)->obj_color(state, object5, 8)->obj_color(state, object6, 8)->obj_color(state, object7, 8)->obj_color(state, object8, 8)->obj_color(state, object9, 8)->obj_color(state, object10, 8)->obj_color(state, object11, 8)",
                "obj_color(state, object3, 8)->obj_color(state, object4, 8)->obj_color(state, object5, 8)->obj_color(state, object6, 8)->obj_color(state, object7, 8)->obj_color(state, object8, 8)->obj_color(state, object9, 8)->obj_color(state, object10, 8)->obj_color(state, object11, 8)",
                "obj_color(state, object3, 8)->obj_color(state, object4, 8)->obj_color(state, object5, 8)->obj_color(state, object6, 8)->obj_color(state, object7, 8)->obj_color(state, object8, 8)->obj_color(state, object9, 8)->obj_color(state, object10, 8)->obj_color(state, object11, 8)",
                "obj_color(state, object3, 8)->obj_color(state, object4, 8)->obj_color(state, object5, 8)->obj_color(state, object6, 8)->obj_color(state, object7, 8)->obj_color(state, object8, 8)->obj_color(state, object9, 8)->obj_color(state, object10, 8)->obj_color(state, object11, 8)",
                "obj_color(state, object3, 8)->obj_color(state, object4, 8)->obj_color(state, object5, 8)->obj_color(state, object6, 8)->obj_color(state, object7, 8)->obj_color(state, object8, 8)->obj_color(state, object9, 8)->obj_color(state, object10, 8)->obj_color(state, object11, 8)",
                "obj_color(state, object3, 8)->obj_color(state, object4, 8)->obj_color(state, object5, 8)->obj_color(state, object6, 8)->obj_color(state, object7, 8)->obj_color(state, object8, 8)->obj_color(state, object9, 8)->obj_color(state, object10, 8)->obj_color(state, object11, 8)"
            ],
            "values": [
                20.0,
                20.0,
                20.0,
                20.0,
                20.0,
                20.0
            ],
            "select_new_ys": [
                "obj_color(state, object3, 8)->obj_color(state, object4, 8)->obj_color(state, object5, 8)->obj_color(state, object6, 8)->obj_color(state, object7, 8)->obj_color(state, object8, 8)->obj_color(state, object9, 8)->obj_color(state, object10, 8)->obj_color(state, object11, 8)",
                "obj_color(state, object3, 8)->obj_color(state, object4, 8)->obj_color(state, object5, 8)->obj_color(state, object6, 8)->obj_color(state, object7, 8)->obj_color(state, object8, 8)->obj_color(state, object9, 8)->obj_color(state, object10, 8)->obj_color(state, object11, 8)"
            ]
        },
        {
            "step": 9,
            "dsl_ys": [
                "obj_color(state, object3, 8)->obj_color(state, object4, 8)->obj_color(state, object5, 8)->obj_color(state, object6, 8)->obj_color(state, object7, 8)->obj_color(state, object8, 8)->obj_color(state, object9, 8)->obj_color(state, object10, 8)->obj_color(state, object11, 8)",
                "obj_color(state, object3, 8)->obj_color(state, object4, 8)->obj_color(state, object5, 8)->obj_color(state, object6, 8)->obj_color(state, object7, 8)->obj_color(state, object8, 8)->obj_color(state, object9, 8)->obj_color(state, object10, 8)->obj_color(state, object11, 8)"
            ],
            "new_dsl_ys": [
                "obj_color(state, object3, 8)->obj_color(state, object4, 8)->obj_color(state, object5, 8)->obj_color(state, object6, 8)->obj_color(state, object7, 8)->obj_color(state, object8, 8)->obj_color(state, object9, 8)->obj_color(state, object10, 8)->obj_color(state, object11, 8)->complete(state)",
                "obj_color(state, object3, 8)->obj_color(state, object4, 8)->obj_color(state, object5, 8)->obj_color(state, object6, 8)->obj_color(state, object7, 8)->obj_color(state, object8, 8)->obj_color(state, object9, 8)->obj_color(state, object10, 8)->obj_color(state, object11, 8)->complete(current_state)",
                "obj_color(state, object3, 8)->obj_color(state, object4, 8)->obj_color(state, object5, 8)->obj_color(state, object6, 8)->obj_color(state, object7, 8)->obj_color(state, object8, 8)->obj_color(state, object9, 8)->obj_color(state, object10, 8)->obj_color(state, object11, 8)->complete([[0, 0, 0, 0, 2, 0, 0, 0, 5], [0, 8, 0, 0, 0, 0, 8, 8, 0], [0, 8, 0, 0, 0, 0, 0, 0, 0], [0, 0, 0, 0, 8, 0, 0, 0, 8], [8, 0, 0, 8, 0, 0, 0, 0, 0], [0, 0, 0, 0, 0, 0, 0, 8, 0], [8, 8, 0, 0, 0, 8, 0, 8, 0]])",
                "obj_color(state, object3, 8)->obj_color(state, object4, 8)->obj_color(state, object5, 8)->obj_color(state, object6, 8)->obj_color(state, object7, 8)->obj_color(state, object8, 8)->obj_color(state, object9, 8)->obj_color(state, object10, 8)->obj_color(state, object11, 8)->complete([[0, 0, 0, 0, 2, 0, 0, 0, 5], [0, 8, 0, 0, 0, 0, 8, 8, 0], [0, 8, 0, 0, 0, 0, 0, 0, 0], [0, 0, 0, 0, 8, 0, 0, 0, 8], [8, 0, 0, 8, 0, 0, 0, 0, 0], [0, 0, 0, 0, 0, 0, 0, 8, 0], [8, 8, 0, 0, 0, 8, 0, 8, 0]])",
                "obj_color(state, object3, 8)->obj_color(state, object4, 8)->obj_color(state, object5, 8)->obj_color(state, object6, 8)->obj_color(state, object7, 8)->obj_color(state, object8, 8)->obj_color(state, object9, 8)->obj_color(state, object10, 8)->obj_color(state, object11, 8)->complete(state)",
                "obj_color(state, object3, 8)->obj_color(state, object4, 8)->obj_color(state, object5, 8)->obj_color(state, object6, 8)->obj_color(state, object7, 8)->obj_color(state, object8, 8)->obj_color(state, object9, 8)->obj_color(state, object10, 8)->obj_color(state, object11, 8)->complete([[0, 0, 0, 0, 2, 0, 0, 0, 5], [0, 8, 0, 0, 0, 0, 8, 8, 0], [0, 8, 0, 0, 0, 0, 0, 0, 0], [0, 0, 0, 0, 8, 0, 0, 0, 8], [8, 0, 0, 8, 0, 0, 0, 0, 0], [0, 0, 0, 0, 0, 0, 0, 8, 0], [8, 8, 0, 0, 0, 8, 0, 8, 0]])"
            ],
            "values": [
                20.0,
                0.0,
                20.0,
                20.0,
                20.0,
                20.0
            ],
            "select_new_ys": [
                "obj_color(state, object3, 8)->obj_color(state, object4, 8)->obj_color(state, object5, 8)->obj_color(state, object6, 8)->obj_color(state, object7, 8)->obj_color(state, object8, 8)->obj_color(state, object9, 8)->obj_color(state, object10, 8)->obj_color(state, object11, 8)->complete(state)",
                "obj_color(state, object3, 8)->obj_color(state, object4, 8)->obj_color(state, object5, 8)->obj_color(state, object6, 8)->obj_color(state, object7, 8)->obj_color(state, object8, 8)->obj_color(state, object9, 8)->obj_color(state, object10, 8)->obj_color(state, object11, 8)->complete([[0, 0, 0, 0, 2, 0, 0, 0, 5], [0, 8, 0, 0, 0, 0, 8, 8, 0], [0, 8, 0, 0, 0, 0, 0, 0, 0], [0, 0, 0, 0, 8, 0, 0, 0, 8], [8, 0, 0, 8, 0, 0, 0, 0, 0], [0, 0, 0, 0, 0, 0, 0, 8, 0], [8, 8, 0, 0, 0, 8, 0, 8, 0]])"
            ]
        }
    ]
}